awsglue/README.md
awsglue/__init__.py
awsglue/context.py
awsglue/data_sink.py
awsglue/data_source.py
awsglue/dataframe_transforms/__init__.py
awsglue/dataframe_transforms/apply_mapping.py
awsglue/dataframereader.py
awsglue/dataframewriter.py
awsglue/devutils.py
awsglue/dynamicframe.py
awsglue/functions.py
awsglue/glue_shell.py
awsglue/gluetypes.py
awsglue/job.py
awsglue/scripts/__init__.py
awsglue/scripts/activate_etl_connector.py
awsglue/scripts/connector_activation_util.py
awsglue/scripts/crawler_redo_from_backup.py
awsglue/scripts/crawler_undo.py
awsglue/scripts/scripts_utils.py
awsglue/streaming_data_source.py
awsglue/transforms/__init__.py
awsglue/transforms/apply_mapping.py
awsglue/transforms/coalesce.py
awsglue/transforms/collection_transforms.py
awsglue/transforms/drop_nulls.py
awsglue/transforms/dynamicframe_filter.py
awsglue/transforms/dynamicframe_map.py
awsglue/transforms/errors_as_dynamicframe.py
awsglue/transforms/field_transforms.py
awsglue/transforms/relationalize.py
awsglue/transforms/repartition.py
awsglue/transforms/resolve_choice.py
awsglue/transforms/transform.py
awsglue/transforms/unbox.py
awsglue/transforms/union.py
awsglue/transforms/unnest_frame.py
awsglue/utils.py
awsglue_local_dev-1.0.0.dist-info/LICENSE.txt
awsglue_local_dev-1.0.0.dist-info/METADATA
awsglue_local_dev-1.0.0.dist-info/WHEEL
awsglue_local_dev-1.0.0.dist-info/RECORD
