Metadata-Version: 2.1
Name: awsglue-local-dev
Version: 1.0.0
Summary: Build Python interfaces to the AWS Glue ETL library for use as a local dependency.
Home-page: https://github.com/dataseedug/aws-glue-libs/tree/glue-4.0
License: Amazon Software License 1.0
Author: Álvaro Brito
Author-email: alvaro.brito@dataseed.de
Requires-Python: >=3,<3.11
Classifier: License :: Other/Proprietary License
Classifier: Programming Language :: Python :: 3
Classifier: Programming Language :: Python :: 3.4
Classifier: Programming Language :: Python :: 3.5
Classifier: Programming Language :: Python :: 3.6
Classifier: Programming Language :: Python :: 3.7
Classifier: Programming Language :: Python :: 3.8
Classifier: Programming Language :: Python :: 3.9
Classifier: Programming Language :: Python :: 3.10
Requires-Dist: pyspark (>=3.3,<4.0)
Project-URL: Repository, https://github.com/dataseedug/aws-glue-libs/tree/glue-4.0
